xmath/__init__.py
xmath-1.1.dist-info/LICENSE.txt
xmath-1.1.dist-info/METADATA
xmath-1.1.dist-info/WHEEL
xmath-1.1.dist-info/top_level.txt
xmath-1.1.dist-info/RECORD
