Metadata-Version: 2.1
Name: xmath
Version: 1.1
Summary: Awesome library to access mathematical functions basic to advanced. Many lots of functions added to this module
Home-page: UNKNOWN
Author: Abul Aiman Shaa
Author-email: shaaimanaalik@gmail.com
License: UNKNOWN
Platform: UNKNOWN
Classifier: Programming Language :: Python :: 3
Classifier: License :: OSI Approved :: MIT License
Classifier: Operating System :: OS Independent
